zepster/__init__.py
zepster/gencatalog.py
zepster/generml.py
zepster/genpyenums.py
zepster/genschema.py
zepster/json_schema_erml.py
zepster/json_schema_graphml.py
zepster/util.py
zepster-0.1.1.dist-info/LICENSE
zepster-0.1.1.dist-info/METADATA
zepster-0.1.1.dist-info/WHEEL
zepster-0.1.1.dist-info/top_level.txt
zepster-0.1.1.dist-info/RECORD
