Metadata-Version: 2.1
Name: zepster
Version: 0.1.1
Summary: Generate data-related artifacts from an Entity-Relationship diagram
Home-page: https://github.com/cisco/zepster
Author: Steven Hand
Author-email: zepster@datasciguy.com
License: Apache
Keywords: database data er entity relationship diagram model modeling MDE
Platform: UNKNOWN
Classifier: Programming Language :: Python
Classifier: License :: OSI Approved :: Apache Software License
Classifier: Topic :: Database
Requires-Dist: cardinality
Requires-Dist: click
Requires-Dist: jsonschema
Requires-Dist: loguru
Requires-Dist: PyYAML
Requires-Dist: toposort
